app/__init__.py
app/cli.py
app/main.py
app/auth/__init__.py
app/auth/auth.py
app/configs/__init__.py
app/configs/configs.py
app/db/__init__.py
app/db/db.py
app/models/__init__.py
app/models/models.py
app/routes/__init__.py
app/routes/api.py
app/routes/applications.py
app/routes/configroutes.py
app/routes/enviro.py
app/routes/websockets.py
app/services/__init__.py
app/services/process_manager.py
app/static/js/script.js
app/static/svg/atlas.svg
app/templates/base.html
app/templates/config.html
app/templates/index.html
app/templates/login.html
app/templates/logs_terminal.html
app/templates/new_application.html
app/templates/register.html
app/templates/view_application.html
app/utils/__init__.py
app/utils/utils.py
atlasserver-0.3.2.dist-info/licenses/LICENSE
atlasserver-0.3.2.dist-info/METADATA
atlasserver-0.3.2.dist-info/WHEEL
atlasserver-0.3.2.dist-info/entry_points.txt
atlasserver-0.3.2.dist-info/top_level.txt
atlasserver-0.3.2.dist-info/RECORD
