Metadata-Version: 2.4
Name: atlasserver
Version: 0.3.2
Summary: Fast Deploy Manager for demo apps made with Flask, FastAPI, and Django
Author-email: AtlasServer-Core / Fredy <riveraaai200678@gmail.com>
License: Apache License 2.0
Project-URL: Homepage, https://github.com/AtlasServer-Core/AtlasServer-Core
Project-URL: Issues, https://github.com/AtlasServer-Core/AtlasServer-Core/issues
Keywords: flask,fastapi,django,deploy,demo
Classifier: Development Status :: 4 - Beta
Classifier: Programming Language :: Python :: 3
Classifier: Programming Language :: Python :: 3.8
Classifier: Programming Language :: Python :: 3.9
Classifier: Programming Language :: Python :: 3.10
Classifier: License :: OSI Approved :: Apache Software License
Classifier: Operating System :: OS Independent
Classifier: Environment :: Web Environment
Classifier: Topic :: Software Development :: Build Tools
Requires-Python: >=3.8
License-File: LICENSE
Requires-Dist: Flask
Requires-Dist: Werkzeug
Requires-Dist: Jinja2
Requires-Dist: bcrypt==4.0.1
Requires-Dist: passlib
Requires-Dist: fastapi
Requires-Dist: uvicorn
Requires-Dist: waitress
Requires-Dist: sqlalchemy
Requires-Dist: psutil
Requires-Dist: pydantic
Requires-Dist: python-multipart
Requires-Dist: pyngrok
Requires-Dist: aiofiles
Requires-Dist: gunicorn
Requires-Dist: click>=8.0.0
Requires-Dist: platformdirs
Provides-Extra: dev
Requires-Dist: pytest; extra == "dev"
Requires-Dist: black; extra == "dev"
Requires-Dist: isort; extra == "dev"
Requires-Dist: mypy; extra == "dev"
Dynamic: license-file
